expme/__init__.py
expme/constants.py
expme/payload.py
expme/server.py
expme/util.py
expme/webshell.py
expme-0.0.2.dist-info/METADATA
expme-0.0.2.dist-info/WHEEL
expme-0.0.2.dist-info/licenses/LICENSE
expme-0.0.2.dist-info/RECORD
