Metadata-Version: 2.1
Name: expme
Version: 0.0.2
Summary: A small exp package
Author-email: zema1 <koalrx@gmail.com>
License-File: LICENSE
Classifier: License :: OSI Approved :: MIT License
Classifier: Operating System :: OS Independent
Classifier: Programming Language :: Python :: 3
Requires-Python: >=3.8
Requires-Dist: requests
